NARUTO/__init__.py
NARUTO/Shinobi/__init__.py
NARUTO/Shinobi/message.py
ZJX_NARUTO-0.2.dist-info/METADATA
ZJX_NARUTO-0.2.dist-info/WHEEL
ZJX_NARUTO-0.2.dist-info/top_level.txt
ZJX_NARUTO-0.2.dist-info/RECORD
