Metadata-Version: 2.1
Name: ZJX-NARUTO
Version: 0.2
Summary: zjx
Author: zjx
License: UNKNOWN
Platform: UNKNOWN
